compute_hyperv/__init__.py
compute_hyperv/i18n.py
compute_hyperv/hacking/__init__.py
compute_hyperv/hacking/checks.py
compute_hyperv/nova/README.rst
compute_hyperv/nova/__init__.py
compute_hyperv/nova/block_device_manager.py
compute_hyperv/nova/conf.py
compute_hyperv/nova/constants.py
compute_hyperv/nova/coordination.py
compute_hyperv/nova/driver.py
compute_hyperv/nova/eventhandler.py
compute_hyperv/nova/hostops.py
compute_hyperv/nova/imagecache.py
compute_hyperv/nova/livemigrationops.py
compute_hyperv/nova/migrationops.py
compute_hyperv/nova/pathutils.py
compute_hyperv/nova/pdk.py
compute_hyperv/nova/rdpconsoleops.py
compute_hyperv/nova/serialconsolehandler.py
compute_hyperv/nova/serialconsoleops.py
compute_hyperv/nova/serialproxy.py
compute_hyperv/nova/snapshotops.py
compute_hyperv/nova/vif.py
compute_hyperv/nova/vmops.py
compute_hyperv/nova/volumeops.py
compute_hyperv/nova/cluster/__init__.py
compute_hyperv/nova/cluster/clusterops.py
compute_hyperv/nova/cluster/driver.py
compute_hyperv/nova/cluster/livemigrationops.py
compute_hyperv/nova/cluster/volumeops.py
compute_hyperv/nova/utils/__init__.py
compute_hyperv/nova/utils/placement.py
compute_hyperv/tests/__init__.py
compute_hyperv/tests/fake_instance.py
compute_hyperv/tests/test.py
compute_hyperv/tests/unit/__init__.py
compute_hyperv/tests/unit/test_base.py
compute_hyperv/tests/unit/test_block_device_manager.py
compute_hyperv/tests/unit/test_coordination.py
compute_hyperv/tests/unit/test_driver.py
compute_hyperv/tests/unit/test_eventhandler.py
compute_hyperv/tests/unit/test_hostops.py
compute_hyperv/tests/unit/test_imagecache.py
compute_hyperv/tests/unit/test_livemigrationops.py
compute_hyperv/tests/unit/test_migrationops.py
compute_hyperv/tests/unit/test_pathutils.py
compute_hyperv/tests/unit/test_pdk.py
compute_hyperv/tests/unit/test_rdpconsoleops.py
compute_hyperv/tests/unit/test_serialconsolehandler.py
compute_hyperv/tests/unit/test_serialconsoleops.py
compute_hyperv/tests/unit/test_serialproxy.py
compute_hyperv-16.0.0.dist-info/AUTHORS
compute_hyperv-16.0.0.dist-info/LICENSE
compute_hyperv-16.0.0.dist-info/METADATA
compute_hyperv-16.0.0.dist-info/WHEEL
compute_hyperv-16.0.0.dist-info/entry_points.txt
compute_hyperv-16.0.0.dist-info/pbr.json
compute_hyperv-16.0.0.dist-info/top_level.txt
compute_hyperv-16.0.0.dist-info/RECORD
