Metadata-Version: 2.1
Name: compute-hyperv
Version: 16.0.0
Summary: Hyper-V Nova Driver
Home-page: http://www.cloudbase.it/
Author: Cloudbase Solutions Srl
Author-email: info@cloudbasesolutions.com
License: Apache License, Version 2.0
Keywords: openstack nova hyper-v compute
Platform: UNKNOWN
Classifier: Environment :: OpenStack
Classifier: Intended Audience :: Information Technology
Classifier: Intended Audience :: System Administrators
Classifier: License :: OSI Approved :: Apache Software License
Classifier: Operating System :: Microsoft :: Windows
Classifier: Programming Language :: Python
Classifier: Programming Language :: Python :: Implementation :: CPython
Classifier: Programming Language :: Python :: 3 :: Only
Classifier: Programming Language :: Python :: 3
Classifier: Programming Language :: Python :: 3.5
Classifier: Programming Language :: Python :: 3.6
Classifier: Programming Language :: Python :: 3.7
Classifier: Programming Language :: Python :: 3.8
Requires-Python: >=3.6
Requires-Dist: eventlet (>=0.30.1)
Requires-Dist: os-brick (>=4.3.1)
Requires-Dist: os-win (>=5.4.0)
Requires-Dist: oslo.config (>=8.6.0)
Requires-Dist: oslo.i18n (>=5.0.1)
Requires-Dist: oslo.log (>=4.4.0)
Requires-Dist: oslo.serialization (>=4.1.0)
Requires-Dist: oslo.service (>=2.5.0)
Requires-Dist: oslo.utils (>=4.8.0)
Requires-Dist: pbr (>=5.5.1)
Requires-Dist: python-barbicanclient (>=4.5.2)
Requires-Dist: tooz (>=1.58.0)
